actual_orm/__init__.py
actual_orm/cli/__init__.py
actual_orm/cli/commands/init.py
actual_orm/cli/commands/migrate_create.py
actual_orm/cli/commands/migrate_dev.py
actual_orm/cli/commands/migrate_prod.py
actual_orm/cli/commands/migrate_reset.py
actual_orm/cli/main.py
actual_orm/cli/utils/__init__.py
actual_orm/cli/utils/action.py
actual_orm/cli/utils/database_schema.py
actual_orm/cli/utils/dynamic_import.py
actual_orm/cli/utils/get_database_url.py
actual_orm/cli/utils/get_models.py
actual_orm/cli/utils/model_schema.py
actual_orm/cli/utils/run_migrations.py
actual_orm/cli/utils/schema.py
actual_orm/cli/utils/schema_differ.py
actual_orm/cli/utils/to_snake_case.py
actual_orm/cli/utils/write_migration.py
actual_orm/connection.py
actual_orm/db/__init__.py
actual_orm/db/data_types.py
actual_orm/db/db.py
actual_orm/db/defaults.py
actual_orm/dot_dict.py
actual_orm/indexes.py
actual_orm/model.py
actual_orm/nanoid.py
actual_orm/query_builder/__init__.py
actual_orm/query_builder/conditions.py
actual_orm/query_builder/model_column.py
actual_orm/query_builder/query_builder.py
actual_orm-1.2.3.dist-info/METADATA
actual_orm-1.2.3.dist-info/WHEEL
actual_orm-1.2.3.dist-info/entry_points.txt
actual_orm-1.2.3.dist-info/RECORD
