Metadata-Version: 2.1
Name: actual-orm
Version: 1.2.3
Summary: 
Author: Matt Sessions
Author-email: me@matthewsessions.com
Requires-Python: >=3.12,<4.0
Classifier: Programming Language :: Python :: 3
Classifier: Programming Language :: Python :: 3.12
Classifier: Programming Language :: Python :: 3.13
Requires-Dist: asyncpg (>=0.30.0,<0.31.0)
Requires-Dist: click (>=8.1.7,<9.0.0)
Requires-Dist: pytest-asyncio (>=0.24.0,<0.25.0)
Requires-Dist: python-dotenv (>=1.0.1,<2.0.0)
